adafruit_airlift/__init__.py
adafruit_airlift/esp32.py
adafruit_circuitpython_airlift-1.0.19.dist-info/licenses/LICENSE
adafruit_circuitpython_airlift-1.0.19.dist-info/METADATA
adafruit_circuitpython_airlift-1.0.19.dist-info/WHEEL
adafruit_circuitpython_airlift-1.0.19.dist-info/top_level.txt
adafruit_circuitpython_airlift-1.0.19.dist-info/RECORD
