Metadata-Version: 2.4
Name: adafruit-circuitpython-airlift
Version: 1.0.19
Summary: Manage AirLift coprocessors for use with Wifi and Bluetooth
Author-email: Adafruit Industries <circuitpython@adafruit.com>
License: MIT
Project-URL: Homepage, https://github.com/adafruit/Adafruit_CircuitPython_AirLift
Keywords: adafruit,blinka,circuitpython,micropython,airlift,ble
Classifier: Intended Audience :: Developers
Classifier: Topic :: Software Development :: Libraries
Classifier: Topic :: Software Development :: Embedded Systems
Classifier: Topic :: System :: Hardware
Classifier: License :: OSI Approved :: MIT License
Classifier: Programming Language :: Python :: 3
License-File: LICENSE
Requires-Dist: Adafruit-Blinka
Requires-Dist: adafruit-blinka-bleio
Provides-Extra: optional
Dynamic: license-file
